[{"TableName":"venues","CommandType":"INSERT","Command":"{\"insert\":\"venues\",\"documents\":[{\"name\":\"浙大三维网球俱乐部\",\"address\":\"西湖区西溪路161号\",\"district\":\"西湖区\",\"type\":\"室外\",\"courtType\":\"塑胶复合\",\"courtsCount\":5,\"priceWeekday\":\"白天50元/小时\",\"priceWeekend\":\"晚上70元/小时\",\"priceEvening\":\"70元/小时\",\"phone\":\"0571-87951983\",\"hours\":\"06:00-22:00\",\"bookingUrl\":\"\",\"bookingMiniProgram\":\"\",\"bookingAppId\":\"\",\"bookingPagePath\":\"\",\"bookingUrlLink\":\"\",\"tags\":[\"有照明\",\"有休息处\",\"有球具零售\",\"有练习墙\"],\"source\":\"大众点评/百度贴吧\",\"lat\":30.250799999999998,\"lng\":120.1141,\"createdAt\":\"2026-05-18T06:03:05.160Z\",\"updatedAt\":\"2026-05-18T06:03:05.160Z\"}]}"}]